ynab_mcp_server/__init__.py
ynab_mcp_server/server.py
ynab_mcp_server/settings.py
ynab_mcp_server/tool_models.py
ynab_mcp_server/ynab_client.py
ynab_mcp_server-0.2.1.dist-info/METADATA
ynab_mcp_server-0.2.1.dist-info/WHEEL
ynab_mcp_server-0.2.1.dist-info/entry_points.txt
ynab_mcp_server-0.2.1.dist-info/licenses/LICENSE
ynab_mcp_server-0.2.1.dist-info/RECORD
