Metadata-Version: 2.4
Name: ynab-mcp-server
Version: 0.2.1
Summary: YNAB MCP integration for managing budgets and transactions
Project-URL: Homepage, https://github.com/jewen/ynab-mcp
Project-URL: Repository, https://github.com/jewen/ynab-mcp
Project-URL: Issues, https://github.com/jewen/ynab-mcp/issues
Author-email: Jake Ewen <jacobt.ewen@gmail.com>
License-Expression: MIT
License-File: LICENSE
Keywords: AI,LLM,agentic,budget,finance,mcp,ynab
Classifier: Development Status :: 3 - Alpha
Classifier: Intended Audience :: Developers
Classifier: License :: OSI Approved :: MIT License
Classifier: Programming Language :: Python :: 3
Classifier: Programming Language :: Python :: 3.11
Classifier: Topic :: Office/Business :: Financial
Requires-Python: >=3.11
Requires-Dist: mcp>=1.9.4
Requires-Dist: pydantic
Requires-Dist: pydantic-settings
Requires-Dist: ynab
Provides-Extra: test
Requires-Dist: pytest-asyncio>=0.21.0; extra == 'test'
Requires-Dist: pytest-cov>=4.1.0; extra == 'test'
Requires-Dist: pytest>=7.0.0; extra == 'test'
